fuwa/__init__.py
fuwa-1.0.2a0.dist-info/METADATA
fuwa-1.0.2a0.dist-info/WHEEL
fuwa-1.0.2a0.dist-info/top_level.txt
fuwa-1.0.2a0.dist-info/RECORD
