Metadata-Version: 2.1
Name: fuwa
Version: 1.0.2a0
Summary: The advertisement and parent package for the fuwa eco-system
Home-page: https://github.com/fuwa-py/fuwa
Author: justanotherebyte
License: UNKNOWN
Project-URL: Issue Tracker, https://github.com/fuwa-py/fuwa/issues
Platform: UNKNOWN
Classifier: Development Status :: 3 - Alpha
Classifier: License :: OSI Approved :: MIT License
Classifier: Intended Audience :: Developers
Classifier: Natural Language :: English
Classifier: Operating System :: OS Independent
Classifier: Programming Language :: Python :: 3.8
Classifier: Programming Language :: Python :: 3.9
Classifier: Topic :: Internet
Classifier: Topic :: Software Development :: Libraries
Classifier: Topic :: Software Development :: Libraries :: Python Modules
Classifier: Topic :: Utilities
Classifier: Typing :: Typed
Requires-Python: >=3.8.0
Provides-Extra: gateway
Requires-Dist: fuwa-gateway ; extra == 'gateway'
Provides-Extra: http
Requires-Dist: fuwa-http ; extra == 'http'
